<?xml version="1.0" encoding="utf-8" ?><dwsync><file name="comment.tpl.php" server="entrepreneurialdesigns.com//localtrove/" local="3441242748" remote="12033470552" /><file name="fix-ie-rtl.css" server="entrepreneurialdesigns.com//localtrove/" local="3441242748" remote="12033470552" /><file name="fix-ie.css" server="entrepreneurialdesigns.com//localtrove/" local="3441242748" remote="12033470552" /><file name="garland.info" server="entrepreneurialdesigns.com//localtrove/" local="3441244870" remote="12033470552" /><file name="logo.png" server="entrepreneurialdesigns.com//localtrove/" local="3441242748" remote="12033470552" /><file name="maintenance-page.tpl.php" server="entrepreneurialdesigns.com//localtrove/" local="3441242748" remote="12033470552" /><file name="node.tpl.php" server="entrepreneurialdesigns.com//localtrove/" local="3441242748" remote="12033470552" /><file name="page.tpl.php" server="entrepreneurialdesigns.com//localtrove/" local="3441242748" remote="12033470552" /><file name="print.css" server="entrepreneurialdesigns.com//localtrove/" local="3441242748" remote="12033470552" /><file name="screenshot.png" server="entrepreneurialdesigns.com//localtrove/" local="3441242748" remote="12033470552" /><file name="style-rtl.css" server="entrepreneurialdesigns.com//localtrove/" local="3441242748" remote="12033470552" /><file name="style.css" server="entrepreneurialdesigns.com//localtrove/" local="3441242748" remote="12033470552" /><file name="template.php" server="entrepreneurialdesigns.com//localtrove/" local="3441242748" remote="12033470552" /><file name="theme-settings.php" server="entrepreneurialdesigns.com//localtrove/" local="3441242748" remote="12033470552" /></dwsync>