<?xml version="1.0" encoding="utf-8" ?><dwsync><file name="LICENSE.txt" server="entrepreneurialdesigns.com//localtrove/" local="3443400900" remote="20623270084" /><file name="README.txt" server="entrepreneurialdesigns.com//localtrove/" local="3443400900" remote="20623270084" /><file name="global_filter.admin.inc" server="entrepreneurialdesigns.com//localtrove/" local="3443400900" remote="20623270084" /><file name="global_filter.blocks.inc" server="entrepreneurialdesigns.com//localtrove/" local="3443400900" remote="20623270084" /><file name="global_filter.css" server="entrepreneurialdesigns.com//localtrove/" local="3443400900" remote="20623270084" /><file name="global_filter.info" server="entrepreneurialdesigns.com//localtrove/" local="3443400900" remote="20623270084" /><file name="global_filter.install" server="entrepreneurialdesigns.com//localtrove/" local="3443400900" remote="20623270084" /><file name="global_filter.module" server="entrepreneurialdesigns.com//localtrove/" local="3443400900" remote="20623270084" /><file name="global_filter.widgets.inc" server="entrepreneurialdesigns.com//localtrove/" local="3443400900" remote="20623270084" /><file name="global_filter.js" server="entrepreneurialdesigns.com//localtrove/" local="3437773980" remote="20617643164" /><file name="global_filter.storage.inc" server="entrepreneurialdesigns.com//localtrove/" local="3443400900" remote="20623270084" /></dwsync>